{
    "created_at": "Sun Jan 01 08:02:05 +0000 2017",
    "favorite_count": 5,
    "hashtags": [],
    "id": 815468122882838528,
    "id_str": "815468122882838528",
    "lang": "en",
    "media": [
        {
            "display_url": "pic.twitter.com/YVJC9Gm9bH",
            "expanded_url": "https://twitter.com/portoflongbeach/status/815468122882838528/photo/1",
            "id": 815468120076877824,
            "media_url": "http://pbs.twimg.com/media/C1Ef70bWgAAHuBp.jpg",
            "media_url_https": "https://pbs.twimg.com/media/C1Ef70bWgAAHuBp.jpg",
            "type": "photo",
            "url": "https://t.co/YVJC9Gm9bH"
        }
    ],
    "retweet_count": 3,
    "source": "<a href=\"http://www.hootsuite.com\" rel=\"nofollow\">Hootsuite</a>",
    "text": "Happy New Year from the Port of Long Beach! https://t.co/YVJC9Gm9bH",
    "urls": [],
    "user": {
        "created_at": "Mon Sep 08 18:02:49 +0000 2008",
        "description": "A major gateway for trans-Pacific trade, the Port of Long Beach is also an industry leader in environmental stewardship. \n\nTerms of Use: https://t.co/vdiVEUcOj2",
        "favourites_count": 636,
        "followers_count": 17224,
        "friends_count": 3705,
        "geo_enabled": true,
        "id": 16188231,
        "lang": "en",
        "listed_count": 500,
        "location": "Long Beach, CA",
        "name": "Port of Long Beach",
        "profile_background_color": "DFFBA2",
        "profile_background_image_url": "http://pbs.twimg.com/profile_background_images/398569138/Aerials_2011-10.jpg",
        "profile_background_tile": true,
        "profile_banner_url": "https://pbs.twimg.com/profile_banners/16188231/1422896225",
        "profile_image_url": "http://pbs.twimg.com/profile_images/540632928665870337/lc--UtlQ_normal.jpeg",
        "profile_link_color": "0084B4",
        "profile_sidebar_fill_color": "D7ECD5",
        "profile_text_color": "333333",
        "screen_name": "portoflongbeach",
        "statuses_count": 7576,
        "time_zone": "Pacific Time (US & Canada)",
        "url": "http://t.co/mpI4vKOimY",
        "utc_offset": -28800,
        "verified": true
    },
    "user_mentions": []
}