{
    "created_at": "Tue Dec 06 21:19:06 +0000 2016",
    "favorite_count": 3,
    "hashtags": [
        {
            "text": "SAVEcard"
        }
    ],
    "id": 806246613735743488,
    "id_str": "806246613735743488",
    "lang": "en",
    "retweet_count": 3,
    "source": "<a href=\"http://twitter.com/download/iphone\" rel=\"nofollow\">Twitter for iPhone</a>",
    "text": "Structure fire on 500 block of Cerritos Ave. 1 family displaced. 1 deceased cat. @RedCrossLBRH requested. #SAVEcard… https://t.co/RpZgtdTdjI",
    "truncated": true,
    "urls": [
        {
            "expanded_url": "https://twitter.com/i/web/status/806246613735743488",
            "url": "https://t.co/RpZgtdTdjI"
        }
    ],
    "user": {
        "created_at": "Tue Jan 13 20:32:26 +0000 2009",
        "description": "Official Long Beach Fire Department Twitter feed. Serving our Community since 1897. Emergency incident updates and public safety information. Semper Paratus.",
        "favourites_count": 566,
        "followers_count": 4876,
        "friends_count": 185,
        "geo_enabled": true,
        "id": 18952042,
        "lang": "en",
        "listed_count": 183,
        "location": "Long Beach, CA",
        "name": "Long Beach Fire",
        "profile_background_color": "1A1B1F",
        "profile_background_image_url": "http://abs.twimg.com/images/themes/theme9/bg.gif",
        "profile_banner_url": "https://pbs.twimg.com/profile_banners/18952042/1468184105",
        "profile_image_url": "http://pbs.twimg.com/profile_images/649810322677567489/PbqyLJlA_normal.jpg",
        "profile_link_color": "2FC2EF",
        "profile_sidebar_fill_color": "252429",
        "profile_text_color": "666666",
        "screen_name": "lbfd",
        "statuses_count": 2277,
        "time_zone": "Pacific Time (US & Canada)",
        "url": "https://t.co/y8zfCjTY2R",
        "utc_offset": -28800
    },
    "user_mentions": [
        {
            "id": 87734643,
            "name": "ARCLongBeachRioHondo",
            "screen_name": "RedCrossLBRH"
        }
    ]
}