{
    "created_at": "Mon Aug 21 20:26:29 +0000 2017",
    "hashtags": [],
    "id": 899729439063367680,
    "id_str": "899729439063367680",
    "lang": "en",
    "retweet_count": 297,
    "retweeted_status": {
        "created_at": "Mon Aug 21 18:57:07 +0000 2017",
        "favorite_count": 1862,
        "hashtags": [],
        "id": 899706951298371584,
        "id_str": "899706951298371584",
        "lang": "en",
        "retweet_count": 297,
        "source": "<a href=\"http://twitter.com/download/iphone\" rel=\"nofollow\">Twitter for iPhone</a>",
        "text": "Okay everybody, eclipse over - let's go back to staring at our phones",
        "urls": [],
        "user": {
            "created_at": "Mon Jun 29 14:25:30 +0000 2009",
            "description": "Mom to Vale and Charley, @TODAYshow Co-Anchor, Recovering Attorney. Georgetown Law. Co-author, Princesses Wear Pants, Fall 2017 https://t.co/vxrSCoxuBJ.",
            "favourites_count": 8927,
            "followers_count": 827246,
            "friends_count": 886,
            "id": 52070270,
            "lang": "en",
            "listed_count": 3970,
            "location": "New York, NY",
            "name": "Savannah Guthrie",
            "profile_background_color": "FFFFFF",
            "profile_background_image_url": "http://pbs.twimg.com/profile_background_images/378800000075914676/cbfe4d91f63ce407fb281b687e4a572a.jpeg",
            "profile_banner_url": "https://pbs.twimg.com/profile_banners/52070270/1488595501",
            "profile_image_url": "http://pbs.twimg.com/profile_images/812101347927539712/oAG-KjZC_normal.jpg",
            "profile_link_color": "DD2E44",
            "profile_sidebar_fill_color": "DDEEF6",
            "profile_text_color": "333333",
            "screen_name": "SavannahGuthrie",
            "statuses_count": 13033,
            "time_zone": "Eastern Time (US & Canada)",
            "url": "https://t.co/8foeSuVzuu",
            "utc_offset": -14400,
            "verified": true
        },
        "user_mentions": []
    },
    "source": "<a href=\"http://twitter.com/download/iphone\" rel=\"nofollow\">Twitter for iPhone</a>",
    "text": "RT @SavannahGuthrie: Okay everybody, eclipse over - let's go back to staring at our phones",
    "urls": [],
    "user": {
        "created_at": "Sun Dec 14 18:45:09 +0000 2008",
        "default_profile": true,
        "description": "Mayor of @LongBeachCity. Educator. Geek. Follow official mayoral office tweets @LongBeachMayor.",
        "favourites_count": 7949,
        "followers_count": 17631,
        "friends_count": 2287,
        "geo_enabled": true,
        "id": 18120497,
        "lang": "en",
        "listed_count": 271,
        "location": "Long Beach",
        "name": "Robert Garcia",
        "profile_background_color": "C0DEED",
        "profile_background_image_url": "http://abs.twimg.com/images/themes/theme1/bg.png",
        "profile_banner_url": "https://pbs.twimg.com/profile_banners/18120497/1501201381",
        "profile_image_url": "http://pbs.twimg.com/profile_images/864246183853563904/4nTFbfrN_normal.jpg",
        "profile_link_color": "1DA1F2",
        "profile_sidebar_fill_color": "DDEEF6",
        "profile_text_color": "333333",
        "screen_name": "RobertGarciaLB",
        "statuses_count": 11269,
        "time_zone": "Pacific Time (US & Canada)",
        "url": "https://t.co/FYG8w5WQQa",
        "utc_offset": -25200,
        "verified": true
    },
    "user_mentions": [
        {
            "id": 52070270,
            "name": "Savannah Guthrie",
            "screen_name": "SavannahGuthrie"
        }
    ]
}