{
    "created_at": "Wed Nov 23 15:26:49 +0000 2016",
    "hashtags": [],
    "id": 801446914138873857,
    "id_str": "801446914138873857",
    "lang": "en",
    "retweet_count": 9,
    "retweeted_status": {
        "created_at": "Thu Nov 17 20:00:21 +0000 2016",
        "favorite_count": 5,
        "hashtags": [],
        "id": 799341427104722945,
        "id_str": "799341427104722945",
        "lang": "en",
        "retweet_count": 9,
        "source": "<a href=\"http://bufferapp.com\" rel=\"nofollow\">Buffer</a>",
        "text": "Family (including yours) are home for the holidays, which means there's more cars on the road. Be extra careful on… https://t.co/1YxI73BrzD",
        "truncated": true,
        "urls": [
            {
                "expanded_url": "https://twitter.com/i/web/status/799341427104722945",
                "url": "https://t.co/1YxI73BrzD"
            }
        ],
        "user": {
            "created_at": "Wed Sep 21 19:03:19 +0000 2011",
            "description": "The California Office of Traffic Safety’s mission is to administer traffic safety grant funds to reduce traffic deaths, injuries, and economic losses.",
            "favourites_count": 743,
            "followers_count": 8301,
            "friends_count": 385,
            "geo_enabled": true,
            "id": 377545903,
            "lang": "en",
            "listed_count": 182,
            "location": "California",
            "name": "CA Traffic Safety",
            "profile_background_color": "C0DEED",
            "profile_background_image_url": "http://pbs.twimg.com/profile_background_images/857410487/0988b091f14442870a15bdacf3c14f2f.jpeg",
            "profile_banner_url": "https://pbs.twimg.com/profile_banners/377545903/1367427978",
            "profile_image_url": "http://pbs.twimg.com/profile_images/3214341091/a4519c83db5c224c8d56d7f44aaf1317_normal.jpeg",
            "profile_link_color": "0084B4",
            "profile_sidebar_fill_color": "DDEEF6",
            "profile_text_color": "333333",
            "screen_name": "OTS_CA",
            "statuses_count": 2329,
            "time_zone": "Pacific Time (US & Canada)",
            "url": "http://t.co/2oWNDW26hh",
            "utc_offset": -28800,
            "verified": true
        },
        "user_mentions": []
    },
    "source": "<a href=\"http://twitter.com\" rel=\"nofollow\">Twitter Web Client</a>",
    "text": "RT @OTS_CA: Family (including yours) are home for the holidays, which means there's more cars on the road. Be extra careful on the roads. #…",
    "urls": [],
    "user": {
        "created_at": "Tue Jun 23 20:47:20 +0000 2009",
        "description": "LBPD Twitter and Facebook not monitored 24 hours- Call 9-1-1 for Emergencies or (562) 435-6711 Non Emergencies. More at http://t.co/GQVRnWIziU",
        "favourites_count": 4344,
        "followers_count": 8681,
        "friends_count": 428,
        "id": 50097116,
        "lang": "en",
        "listed_count": 232,
        "name": "Long Beach PD",
        "profile_background_color": "C6E2EE",
        "profile_background_image_url": "http://pbs.twimg.com/profile_background_images/636294292/ufit2wb5go47lj69c83s.jpeg",
        "profile_background_tile": true,
        "profile_banner_url": "https://pbs.twimg.com/profile_banners/50097116/1459978362",
        "profile_image_url": "http://pbs.twimg.com/profile_images/640409982031167488/29k4lKDM_normal.jpg",
        "profile_link_color": "63A5BD",
        "profile_sidebar_fill_color": "252429",
        "profile_text_color": "666666",
        "screen_name": "LongBeachPD_CA",
        "statuses_count": 6063,
        "time_zone": "Pacific Time (US & Canada)",
        "url": "http://t.co/mv2Tul1Uz8",
        "utc_offset": -28800
    },
    "user_mentions": [
        {
            "id": 377545903,
            "name": "CA Traffic Safety",
            "screen_name": "OTS_CA"
        }
    ]
}